{
 "bellista-scaling-gel": {
  "chunks": 14,
  "height": 26776,
  "width": 1290
 },
 "bellista-caffeine-shampoo": {
  "chunks": 16,
  "height": 30867,
  "width": 1290
 },
 "bellista-caffeine-treatment": {
  "chunks": 15,
  "height": 29540,
  "width": 1290
 },
 "bellista-3step-set": {
  "chunks": 15,
  "height": 29625,
  "width": 1290
 },
 "bellista-caffeine-tonic": {
  "chunks": 17,
  "height": 32622,
  "width": 1290
 },
 "bellista-eucalyptus-shampoo": {
  "chunks": 12,
  "height": 23830,
  "width": 1290
 },
 "bellista-silk-mist": {
  "chunks": 11,
  "height": 21360,
  "width": 1290
 },
 "bellista-keratin-mist": {
  "chunks": 12,
  "height": 22455,
  "width": 1290
 },
 "bellista-collagen-mist": {
  "chunks": 11,
  "height": 21180,
  "width": 1290
 },
 "bellista-silk-shine-serum": {
  "chunks": 12,
  "height": 23726,
  "width": 1290
 },
 "bellista-keratin-nourish-serum": {
  "chunks": 12,
  "height": 23726,
  "width": 1290
 },
 "bellista-collagen-moist-serum": {
  "chunks": 12,
  "height": 23726,
  "width": 1290
 },
 "bellista-silk-curl-cream": {
  "chunks": 10,
  "height": 19788,
  "width": 1290
 },
 "bellista-keratin-water-pack": {
  "chunks": 12,
  "height": 23310,
  "width": 1290
 },
 "bellista-collagen-aqua-essence": {
  "chunks": 10,
  "height": 18868,
  "width": 1290
 },
 "valentine-magic-straight-system": {
  "locales": { "th": { "chunks": [
   { "file": "hero.webp", "width": 1500, "height": 1050, "sectionId": "hero", "altTh": "Valentine Professional น้ำยา Multi Perm H1 D1 C2 และ L2 ใช้ได้ทั้งดัดดิจิตอล ยืดวอลลุ่ม (วอลลุ่มเมจิก) และรีบอนดิ้ง" }
  ] } }
 },
 "valentine-lpp-treatment": {
  "locales": { "th": { "chunks": [
   { "file": "hero.webp", "width": 1100, "height": 1100, "sectionId": "hero", "altTh": "Valentine Professional L.P.P Treatment แบบล้างออกสำหรับเส้นผมเสีย" }
  ] } }
 },
 "achoa-oneshot-treatment": {
  "chunks": 3,
  "height": 4232,
  "width": 1290
 }
}
